{
  "userProfilePK": 134728532,
  "calendarDate": "2026-05-12",
  "startTimestampGMT": "2026-05-12T05:00:00.0",
  "endTimestampGMT": "2026-05-13T00:08:00.0",
  "startTimestampLocal": "2026-05-12T00:00:00.0",
  "endTimestampLocal": "2026-05-13T00:00:00.0",
  "maxHeartRate": 117,
  "minHeartRate": 52,
  "restingHeartRate": 53,
  "lastSevenDaysAvgRestingHeartRate": 49,
  "heartRateValues": [
    [
      1778562000000,
      80
    ],
    [
      1778562120000,
      73
    ],
    [
      1778562240000,
      79
    ],
    [
      1778562360000,
      79
    ],
    [
      1778562480000,
      63
    ],
    [
      1778562600000,
      63
    ],
    [
      1778562720000,
      62
    ],
    [
      1778562840000,
      64
    ],
    [
      1778562960000,
      64
    ],
    [
      1778563080000,
      65
    ],
    [
      1778563200000,
      64
    ],
    [
      1778563320000,
      64
    ],
    [
      1778563440000,
      60
    ],
    [
      1778563560000,
      62
    ],
    [
      1778563680000,
      65
    ],
    [
      1778563800000,
      63
    ],
    [
      1778563920000,
      64
    ],
    [
      1778564040000,
      62
    ],
    [
      1778564160000,
      67
    ],
    [
      1778564280000,
      63
    ],
    [
      1778564400000,
      64
    ],
    [
      1778564520000,
      64
    ],
    [
      1778564640000,
      67
    ],
    [
      1778564760000,
      67
    ],
    [
      1778564880000,
      65
    ],
    [
      1778565000000,
      64
    ],
    [
      1778565120000,
      63
    ],
    [
      1778565240000,
      63
    ],
    [
      1778565360000,
      64
    ],
    [
      1778565480000,
      57
    ],
    [
      1778565600000,
      58
    ],
    [
      1778565720000,
      59
    ],
    [
      1778565840000,
      57
    ],
    [
      1778565960000,
      56
    ],
    [
      1778566080000,
      57
    ],
    [
      1778566200000,
      56
    ],
    [
      1778566320000,
      57
    ],
    [
      1778566440000,
      57
    ],
    [
      1778566560000,
      56
    ],
    [
      1778566680000,
      57
    ],
    [
      1778566800000,
      56
    ],
    [
      1778566920000,
      56
    ],
    [
      1778567040000,
      57
    ],
    [
      1778567160000,
      55
    ],
    [
      1778567280000,
      55
    ],
    [
      1778567400000,
      56
    ],
    [
      1778567520000,
      59
    ],
    [
      1778567640000,
      57
    ],
    [
      1778567760000,
      56
    ],
    [
      1778567880000,
      55
    ],
    [
      1778568000000,
      57
    ],
    [
      1778568120000,
      55
    ],
    [
      1778568240000,
      57
    ],
    [
      1778568360000,
      55
    ],
    [
      1778568480000,
      56
    ],
    [
      1778568600000,
      56
    ],
    [
      1778568720000,
      56
    ],
    [
      1778568840000,
      57
    ],
    [
      1778568960000,
      57
    ],
    [
      1778569080000,
      57
    ],
    [
      1778569200000,
      56
    ],
    [
      1778569320000,
      56
    ],
    [
      1778569440000,
      58
    ],
    [
      1778569560000,
      56
    ],
    [
      1778569680000,
      57
    ],
    [
      1778569800000,
      59
    ],
    [
      1778569920000,
      59
    ],
    [
      1778570040000,
      59
    ],
    [
      1778570160000,
      59
    ],
    [
      1778570280000,
      58
    ],
    [
      1778570400000,
      54
    ],
    [
      1778570520000,
      56
    ],
    [
      1778570640000,
      56
    ],
    [
      1778570760000,
      58
    ],
    [
      1778570880000,
      54
    ],
    [
      1778571000000,
      60
    ],
    [
      1778571120000,
      59
    ],
    [
      1778571240000,
      61
    ],
    [
      1778571360000,
      60
    ],
    [
      1778571480000,
      60
    ],
    [
      1778571600000,
      58
    ],
    [
      1778571720000,
      52
    ],
    [
      1778571840000,
      56
    ],
    [
      1778571960000,
      57
    ],
    [
      1778572080000,
      56
    ],
    [
      1778572200000,
      59
    ],
    [
      1778572320000,
      63
    ],
    [
      1778572440000,
      67
    ],
    [
      1778572560000,
      61
    ],
    [
      1778572680000,
      54
    ],
    [
      1778572800000,
      55
    ],
    [
      1778572920000,
      58
    ],
    [
      1778573040000,
      52
    ],
    [
      1778573160000,
      55
    ],
    [
      1778573280000,
      54
    ],
    [
      1778573400000,
      55
    ],
    [
      1778573520000,
      55
    ],
    [
      1778573640000,
      54
    ],
    [
      1778573760000,
      54
    ],
    [
      1778573880000,
      55
    ],
    [
      1778574000000,
      55
    ],
    [
      1778574120000,
      55
    ],
    [
      1778574240000,
      54
    ],
    [
      1778574360000,
      55
    ],
    [
      1778574480000,
      55
    ],
    [
      1778574600000,
      56
    ],
    [
      1778574720000,
      56
    ],
    [
      1778574840000,
      56
    ],
    [
      1778574960000,
      61
    ],
    [
      1778575080000,
      55
    ],
    [
      1778575200000,
      54
    ],
    [
      1778575320000,
      55
    ],
    [
      1778575440000,
      56
    ],
    [
      1778575560000,
      57
    ],
    [
      1778575680000,
      57
    ],
    [
      1778575800000,
      57
    ],
    [
      1778575920000,
      55
    ],
    [
      1778576040000,
      55
    ],
    [
      1778576160000,
      55
    ],
    [
      1778576280000,
      57
    ],
    [
      1778576400000,
      53
    ],
    [
      1778576520000,
      55
    ],
    [
      1778576640000,
      55
    ],
    [
      1778576760000,
      56
    ],
    [
      1778576880000,
      59
    ],
    [
      1778577000000,
      57
    ],
    [
      1778577120000,
      58
    ],
    [
      1778577240000,
      61
    ],
    [
      1778577360000,
      62
    ],
    [
      1778577480000,
      54
    ],
    [
      1778577600000,
      59
    ],
    [
      1778577720000,
      55
    ],
    [
      1778577840000,
      56
    ],
    [
      1778577960000,
      56
    ],
    [
      1778578080000,
      54
    ],
    [
      1778578200000,
      54
    ],
    [
      1778578320000,
      55
    ],
    [
      1778578440000,
      53
    ],
    [
      1778578560000,
      55
    ],
    [
      1778578680000,
      54
    ],
    [
      1778578800000,
      54
    ],
    [
      1778578920000,
      54
    ],
    [
      1778579040000,
      53
    ],
    [
      1778579160000,
      54
    ],
    [
      1778579280000,
      55
    ],
    [
      1778579400000,
      54
    ],
    [
      1778579520000,
      54
    ],
    [
      1778579640000,
      55
    ],
    [
      1778579760000,
      53
    ],
    [
      1778579880000,
      54
    ],
    [
      1778580000000,
      59
    ],
    [
      1778580120000,
      52
    ],
    [
      1778580240000,
      52
    ],
    [
      1778580360000,
      52
    ],
    [
      1778580480000,
      53
    ],
    [
      1778580600000,
      52
    ],
    [
      1778580720000,
      60
    ],
    [
      1778580840000,
      54
    ],
    [
      1778580960000,
      53
    ],
    [
      1778581080000,
      58
    ],
    [
      1778581200000,
      52
    ],
    [
      1778581320000,
      53
    ],
    [
      1778581440000,
      57
    ],
    [
      1778581560000,
      61
    ],
    [
      1778581680000,
      57
    ],
    [
      1778581800000,
      52
    ],
    [
      1778581920000,
      56
    ],
    [
      1778582040000,
      57
    ],
    [
      1778582160000,
      57
    ],
    [
      1778582280000,
      60
    ],
    [
      1778582400000,
      57
    ],
    [
      1778582520000,
      55
    ],
    [
      1778582640000,
      56
    ],
    [
      1778582760000,
      57
    ],
    [
      1778582880000,
      58
    ],
    [
      1778583000000,
      55
    ],
    [
      1778583120000,
      56
    ],
    [
      1778583240000,
      56
    ],
    [
      1778583360000,
      57
    ],
    [
      1778583480000,
      59
    ],
    [
      1778583600000,
      57
    ],
    [
      1778583720000,
      55
    ],
    [
      1778583840000,
      57
    ],
    [
      1778583960000,
      57
    ],
    [
      1778584080000,
      57
    ],
    [
      1778584200000,
      58
    ],
    [
      1778584320000,
      57
    ],
    [
      1778584440000,
      57
    ],
    [
      1778584560000,
      57
    ],
    [
      1778584680000,
      56
    ],
    [
      1778584800000,
      61
    ],
    [
      1778584920000,
      53
    ],
    [
      1778585040000,
      57
    ],
    [
      1778585160000,
      54
    ],
    [
      1778585280000,
      52
    ],
    [
      1778585400000,
      53
    ],
    [
      1778585520000,
      52
    ],
    [
      1778585640000,
      53
    ],
    [
      1778585760000,
      54
    ],
    [
      1778585880000,
      54
    ],
    [
      1778586000000,
      54
    ],
    [
      1778586120000,
      67
    ],
    [
      1778586240000,
      54
    ],
    [
      1778586360000,
      53
    ],
    [
      1778586480000,
      54
    ],
    [
      1778586600000,
      55
    ],
    [
      1778586720000,
      54
    ],
    [
      1778586840000,
      59
    ],
    [
      1778586960000,
      53
    ],
    [
      1778587080000,
      56
    ],
    [
      1778587200000,
      58
    ],
    [
      1778587320000,
      60
    ],
    [
      1778587440000,
      58
    ],
    [
      1778587560000,
      60
    ],
    [
      1778587680000,
      55
    ],
    [
      1778587800000,
      65
    ],
    [
      1778587920000,
      54
    ],
    [
      1778588040000,
      56
    ],
    [
      1778588160000,
      58
    ],
    [
      1778588280000,
      55
    ],
    [
      1778588400000,
      57
    ],
    [
      1778588520000,
      56
    ],
    [
      1778588640000,
      65
    ],
    [
      1778588760000,
      54
    ],
    [
      1778588880000,
      54
    ],
    [
      1778589000000,
      59
    ],
    [
      1778589120000,
      64
    ],
    [
      1778589240000,
      54
    ],
    [
      1778589360000,
      54
    ],
    [
      1778589480000,
      53
    ],
    [
      1778589600000,
      54
    ],
    [
      1778589720000,
      55
    ],
    [
      1778589840000,
      52
    ],
    [
      1778589960000,
      62
    ],
    [
      1778590080000,
      58
    ],
    [
      1778590200000,
      53
    ],
    [
      1778590320000,
      68
    ],
    [
      1778590440000,
      52
    ],
    [
      1778590560000,
      52
    ],
    [
      1778590680000,
      59
    ],
    [
      1778590800000,
      52
    ],
    [
      1778590920000,
      65
    ],
    [
      1778591040000,
      66
    ],
    [
      1778591160000,
      81
    ],
    [
      1778591280000,
      83
    ],
    [
      1778591400000,
      73
    ],
    [
      1778591520000,
      91
    ],
    [
      1778591640000,
      74
    ],
    [
      1778591760000,
      74
    ],
    [
      1778591880000,
      84
    ],
    [
      1778592000000,
      null
    ],
    [
      1778593320000,
      87
    ],
    [
      1778593440000,
      93
    ],
    [
      1778593560000,
      99
    ],
    [
      1778593680000,
      101
    ],
    [
      1778593800000,
      100
    ],
    [
      1778593920000,
      104
    ],
    [
      1778594040000,
      99
    ],
    [
      1778594160000,
      97
    ],
    [
      1778594280000,
      102
    ],
    [
      1778594400000,
      108
    ],
    [
      1778594520000,
      117
    ],
    [
      1778594640000,
      101
    ],
    [
      1778594760000,
      75
    ],
    [
      1778594880000,
      77
    ],
    [
      1778595000000,
      75
    ],
    [
      1778595120000,
      71
    ],
    [
      1778595240000,
      72
    ],
    [
      1778595360000,
      73
    ],
    [
      1778595480000,
      79
    ],
    [
      1778595600000,
      71
    ],
    [
      1778595720000,
      75
    ],
    [
      1778595840000,
      81
    ],
    [
      1778595960000,
      73
    ],
    [
      1778596080000,
      77
    ],
    [
      1778596200000,
      78
    ],
    [
      1778596320000,
      80
    ],
    [
      1778596440000,
      73
    ],
    [
      1778596560000,
      73
    ],
    [
      1778596680000,
      76
    ],
    [
      1778596800000,
      80
    ],
    [
      1778596920000,
      76
    ],
    [
      1778597040000,
      79
    ],
    [
      1778597160000,
      82
    ],
    [
      1778597280000,
      78
    ],
    [
      1778597400000,
      77
    ],
    [
      1778597520000,
      74
    ],
    [
      1778597640000,
      72
    ],
    [
      1778597760000,
      77
    ],
    [
      1778597880000,
      73
    ],
    [
      1778598000000,
      77
    ],
    [
      1778598120000,
      84
    ],
    [
      1778598240000,
      69
    ],
    [
      1778598360000,
      72
    ],
    [
      1778598480000,
      70
    ],
    [
      1778598600000,
      85
    ],
    [
      1778598720000,
      73
    ],
    [
      1778598840000,
      80
    ],
    [
      1778598960000,
      72
    ],
    [
      1778599080000,
      74
    ],
    [
      1778599200000,
      79
    ],
    [
      1778599320000,
      79
    ],
    [
      1778599440000,
      72
    ],
    [
      1778599560000,
      80
    ],
    [
      1778599680000,
      85
    ],
    [
      1778599800000,
      80
    ],
    [
      1778599920000,
      null
    ],
    [
      1778600040000,
      71
    ],
    [
      1778600160000,
      null
    ],
    [
      1778600400000,
      79
    ],
    [
      1778600520000,
      77
    ],
    [
      1778600640000,
      75
    ],
    [
      1778600760000,
      73
    ],
    [
      1778600880000,
      80
    ],
    [
      1778601000000,
      81
    ],
    [
      1778601120000,
      75
    ],
    [
      1778601240000,
      85
    ],
    [
      1778601360000,
      73
    ],
    [
      1778601480000,
      76
    ],
    [
      1778601600000,
      78
    ],
    [
      1778601720000,
      79
    ],
    [
      1778601840000,
      94
    ],
    [
      1778601960000,
      91
    ],
    [
      1778602080000,
      81
    ],
    [
      1778602200000,
      79
    ],
    [
      1778602320000,
      77
    ],
    [
      1778602440000,
      80
    ],
    [
      1778602560000,
      78
    ],
    [
      1778602680000,
      76
    ],
    [
      1778602800000,
      83
    ],
    [
      1778602920000,
      88
    ],
    [
      1778603040000,
      87
    ],
    [
      1778603160000,
      85
    ],
    [
      1778603280000,
      78
    ],
    [
      1778603400000,
      77
    ],
    [
      1778603520000,
      71
    ],
    [
      1778603640000,
      77
    ],
    [
      1778603760000,
      76
    ],
    [
      1778603880000,
      73
    ],
    [
      1778604000000,
      75
    ],
    [
      1778604120000,
      73
    ],
    [
      1778604240000,
      73
    ],
    [
      1778604360000,
      74
    ],
    [
      1778604480000,
      71
    ],
    [
      1778604600000,
      77
    ],
    [
      1778604720000,
      73
    ],
    [
      1778604840000,
      72
    ],
    [
      1778604960000,
      70
    ],
    [
      1778605080000,
      72
    ],
    [
      1778605200000,
      72
    ],
    [
      1778605320000,
      76
    ],
    [
      1778605440000,
      70
    ],
    [
      1778605560000,
      69
    ],
    [
      1778605680000,
      70
    ],
    [
      1778605800000,
      71
    ],
    [
      1778605920000,
      73
    ],
    [
      1778606040000,
      74
    ],
    [
      1778606160000,
      74
    ],
    [
      1778606280000,
      70
    ],
    [
      1778606400000,
      70
    ],
    [
      1778606520000,
      73
    ],
    [
      1778606640000,
      66
    ],
    [
      1778606760000,
      73
    ],
    [
      1778606880000,
      71
    ],
    [
      1778607000000,
      68
    ],
    [
      1778607120000,
      69
    ],
    [
      1778607240000,
      72
    ],
    [
      1778607360000,
      75
    ],
    [
      1778607480000,
      77
    ],
    [
      1778607600000,
      82
    ],
    [
      1778607720000,
      82
    ],
    [
      1778607840000,
      83
    ],
    [
      1778607960000,
      69
    ],
    [
      1778608080000,
      77
    ],
    [
      1778608200000,
      74
    ],
    [
      1778608320000,
      81
    ],
    [
      1778608440000,
      71
    ],
    [
      1778608560000,
      73
    ],
    [
      1778608680000,
      72
    ],
    [
      1778608800000,
      82
    ],
    [
      1778608920000,
      76
    ],
    [
      1778609040000,
      75
    ],
    [
      1778609160000,
      75
    ],
    [
      1778609280000,
      72
    ],
    [
      1778609400000,
      73
    ],
    [
      1778609520000,
      75
    ],
    [
      1778609640000,
      72
    ],
    [
      1778609760000,
      74
    ],
    [
      1778609880000,
      73
    ],
    [
      1778610000000,
      69
    ],
    [
      1778610120000,
      71
    ],
    [
      1778610240000,
      73
    ],
    [
      1778610360000,
      70
    ],
    [
      1778610480000,
      74
    ],
    [
      1778610600000,
      89
    ],
    [
      1778610720000,
      73
    ],
    [
      1778610840000,
      76
    ],
    [
      1778610960000,
      75
    ],
    [
      1778611080000,
      67
    ],
    [
      1778611200000,
      67
    ],
    [
      1778611320000,
      67
    ],
    [
      1778611440000,
      74
    ],
    [
      1778611560000,
      76
    ],
    [
      1778611680000,
      75
    ],
    [
      1778611800000,
      70
    ],
    [
      1778611920000,
      71
    ],
    [
      1778612040000,
      70
    ],
    [
      1778612160000,
      71
    ],
    [
      1778612280000,
      74
    ],
    [
      1778612400000,
      65
    ],
    [
      1778612520000,
      70
    ],
    [
      1778612640000,
      69
    ],
    [
      1778612760000,
      69
    ],
    [
      1778612880000,
      68
    ],
    [
      1778613000000,
      72
    ],
    [
      1778613120000,
      68
    ],
    [
      1778613240000,
      71
    ],
    [
      1778613360000,
      72
    ],
    [
      1778613480000,
      70
    ],
    [
      1778613600000,
      70
    ],
    [
      1778613720000,
      69
    ],
    [
      1778613840000,
      67
    ],
    [
      1778613960000,
      71
    ],
    [
      1778614080000,
      61
    ],
    [
      1778614200000,
      66
    ],
    [
      1778614320000,
      69
    ],
    [
      1778614440000,
      69
    ],
    [
      1778614560000,
      65
    ],
    [
      1778614680000,
      73
    ],
    [
      1778614800000,
      74
    ],
    [
      1778614920000,
      74
    ],
    [
      1778615040000,
      78
    ],
    [
      1778615160000,
      84
    ],
    [
      1778615280000,
      86
    ],
    [
      1778615400000,
      91
    ],
    [
      1778615520000,
      89
    ],
    [
      1778615640000,
      80
    ],
    [
      1778615760000,
      79
    ],
    [
      1778615880000,
      77
    ],
    [
      1778616000000,
      76
    ],
    [
      1778616120000,
      74
    ],
    [
      1778616240000,
      73
    ],
    [
      1778616360000,
      78
    ],
    [
      1778616480000,
      83
    ],
    [
      1778616600000,
      86
    ],
    [
      1778616720000,
      84
    ],
    [
      1778616840000,
      74
    ],
    [
      1778616960000,
      68
    ],
    [
      1778617080000,
      64
    ],
    [
      1778617200000,
      75
    ],
    [
      1778617320000,
      71
    ],
    [
      1778617440000,
      75
    ],
    [
      1778617560000,
      71
    ],
    [
      1778617680000,
      66
    ],
    [
      1778617800000,
      74
    ],
    [
      1778617920000,
      73
    ],
    [
      1778618040000,
      70
    ],
    [
      1778618160000,
      69
    ],
    [
      1778618280000,
      72
    ],
    [
      1778618400000,
      70
    ],
    [
      1778618520000,
      68
    ],
    [
      1778618640000,
      67
    ],
    [
      1778618760000,
      71
    ],
    [
      1778618880000,
      69
    ],
    [
      1778619000000,
      68
    ],
    [
      1778619120000,
      70
    ],
    [
      1778619240000,
      78
    ],
    [
      1778619360000,
      66
    ],
    [
      1778619480000,
      73
    ],
    [
      1778619600000,
      82
    ],
    [
      1778619720000,
      67
    ],
    [
      1778619840000,
      78
    ],
    [
      1778619960000,
      80
    ],
    [
      1778620080000,
      80
    ],
    [
      1778620200000,
      85
    ],
    [
      1778620320000,
      75
    ],
    [
      1778620440000,
      75
    ],
    [
      1778620560000,
      76
    ],
    [
      1778620680000,
      77
    ],
    [
      1778620800000,
      68
    ],
    [
      1778620920000,
      74
    ],
    [
      1778621040000,
      75
    ],
    [
      1778621160000,
      71
    ],
    [
      1778621280000,
      72
    ],
    [
      1778621400000,
      66
    ],
    [
      1778621520000,
      79
    ],
    [
      1778621640000,
      77
    ],
    [
      1778621760000,
      72
    ],
    [
      1778621880000,
      73
    ],
    [
      1778622000000,
      77
    ],
    [
      1778622120000,
      76
    ],
    [
      1778622240000,
      71
    ],
    [
      1778622360000,
      75
    ],
    [
      1778622480000,
      77
    ],
    [
      1778622600000,
      75
    ],
    [
      1778622720000,
      70
    ],
    [
      1778622840000,
      72
    ],
    [
      1778622960000,
      73
    ],
    [
      1778623080000,
      72
    ],
    [
      1778623200000,
      79
    ],
    [
      1778623320000,
      72
    ],
    [
      1778623440000,
      73
    ],
    [
      1778623560000,
      70
    ],
    [
      1778623680000,
      70
    ],
    [
      1778623800000,
      69
    ],
    [
      1778623920000,
      72
    ],
    [
      1778624040000,
      69
    ],
    [
      1778624160000,
      79
    ],
    [
      1778624280000,
      73
    ],
    [
      1778624400000,
      68
    ],
    [
      1778624520000,
      70
    ],
    [
      1778624640000,
      68
    ],
    [
      1778624760000,
      66
    ],
    [
      1778624880000,
      66
    ],
    [
      1778625000000,
      69
    ],
    [
      1778625120000,
      73
    ],
    [
      1778625240000,
      68
    ],
    [
      1778625360000,
      68
    ],
    [
      1778625480000,
      69
    ],
    [
      1778625600000,
      72
    ],
    [
      1778625720000,
      78
    ],
    [
      1778625840000,
      67
    ],
    [
      1778625960000,
      69
    ],
    [
      1778626080000,
      69
    ],
    [
      1778626200000,
      65
    ],
    [
      1778626320000,
      67
    ],
    [
      1778626440000,
      70
    ],
    [
      1778626560000,
      67
    ],
    [
      1778626680000,
      72
    ],
    [
      1778626800000,
      69
    ],
    [
      1778626920000,
      69
    ],
    [
      1778627040000,
      71
    ],
    [
      1778627160000,
      79
    ],
    [
      1778627280000,
      85
    ],
    [
      1778627400000,
      78
    ],
    [
      1778627520000,
      75
    ],
    [
      1778627640000,
      85
    ],
    [
      1778627760000,
      92
    ],
    [
      1778627880000,
      94
    ],
    [
      1778628000000,
      100
    ],
    [
      1778628120000,
      97
    ],
    [
      1778628240000,
      99
    ],
    [
      1778628360000,
      99
    ],
    [
      1778628480000,
      93
    ],
    [
      1778628600000,
      92
    ],
    [
      1778628720000,
      83
    ],
    [
      1778628840000,
      77
    ],
    [
      1778628960000,
      89
    ],
    [
      1778629080000,
      74
    ],
    [
      1778629200000,
      78
    ],
    [
      1778629320000,
      88
    ],
    [
      1778629440000,
      87
    ],
    [
      1778629560000,
      78
    ],
    [
      1778629680000,
      88
    ],
    [
      1778629800000,
      96
    ],
    [
      1778629920000,
      93
    ],
    [
      1778630040000,
      79
    ],
    [
      1778630160000,
      79
    ],
    [
      1778630280000,
      100
    ],
    [
      1778630400000,
      100
    ],
    [
      1778630520000,
      99
    ],
    [
      1778630640000,
      93
    ],
    [
      1778630760000,
      93
    ]
  ],
  "heartRateValueDescriptors": [
    {
      "index": 0,
      "key": "timestamp"
    },
    {
      "index": 1,
      "key": "heartrate"
    }
  ]
}